check_version.py
updater/VERSION
updater/__init__.py
updater/components.py
updater/config_yaml.py
updater-0.3.2.dist-info/METADATA
updater-0.3.2.dist-info/WHEEL
updater-0.3.2.dist-info/entry_points.txt
updater-0.3.2.dist-info/top_level.txt
updater-0.3.2.dist-info/RECORD
