Metadata-Version: 2.1
Name: updater
Version: 0.3.2
Summary: Check and update versions of pypi packages and docker-images in your project.
Home-page: https://github.com/paterit/version-checker
Author: PaterIT
Author-email: paterit@gmail.com
License: MIT
Platform: UNKNOWN
Classifier: Development Status :: 3 - Alpha
Classifier: License :: OSI Approved :: MIT License
Classifier: Programming Language :: Python
Classifier: Programming Language :: Python :: 3 :: Only
Classifier: Programming Language :: Python :: 3.10
Classifier: Programming Language :: Python :: 3.9
Classifier: Programming Language :: Python :: 3.8
Classifier: Programming Language :: Python :: 3.7
Classifier: Programming Language :: Python :: 3.6
Classifier: Topic :: Software Development :: Build Tools
Classifier: Operating System :: POSIX :: Linux
Requires-Python: >=3.6.9
